iamport/__init__.py
iamport/client.py
iamport/client.pyi
iamport_rest_client-0.9.0.dist-info/LICENSE
iamport_rest_client-0.9.0.dist-info/METADATA
iamport_rest_client-0.9.0.dist-info/WHEEL
iamport_rest_client-0.9.0.dist-info/top_level.txt
iamport_rest_client-0.9.0.dist-info/RECORD
