Metadata-Version: 2.1
Name: iamport-rest-client
Version: 0.9.0
Summary: REST client for I'mport;(http://www.iamport.kr)
Home-page: https://github.com/iamport/iamport-rest-client-python
Author: PerhapsSPY
Author-email: perhapsspy@gmail.com
License: MIT
Project-URL: Bug Tracker, https://github.com/iamport/iamport-rest-client-python/issues
Platform: UNKNOWN
Classifier: Programming Language :: Python :: 3
Classifier: License :: OSI Approved :: MIT License
Classifier: Operating System :: OS Independent
Classifier: Programming Language :: Python
Classifier: Programming Language :: Python :: 3.6
Classifier: Programming Language :: Python :: 3.7
Classifier: Programming Language :: Python :: 3.8
Classifier: Programming Language :: Python :: 3.9
Classifier: Programming Language :: Python :: Implementation :: CPython
Classifier: Programming Language :: Python :: Implementation :: PyPy
Classifier: Topic :: Software Development :: Libraries :: Python Modules
Requires-Python: >=3.6
Provides-Extra: dev
License-File: LICENSE
